[
  {
    "Id": "1",
    "Nom": "Chai",
    "FournisseurID": "1",
    "CategorieID": "1",
    "QuantitieParUnite": "10 boxes x 20 bags",
    "PrixUnitaire": "18.0000",
    "UnityDansStock": "39"
  },
  {
    "Id": "2",
    "Nom": "Chang",
    "FournisseurID": "1",
    "CategorieID": "1",
    "QuantitieParUnite": "24 - 12 oz bottles",
    "PrixUnitaire": "19.0000",
    "UnityDansStock": "17"
  },
  {
    "Id": "3",
    "Nom": "Aniseed Syrup",
    "FournisseurID": "1",
    "CategorieID": "2",
    "QuantitieParUnite": "12 - 550 ml bottles",
    "PrixUnitaire": "10.0000",
    "UnityDansStock": "13"
  },
  {
    "Id": "4",
    "Nom": "Chef Anton's Cajun Seasoning",
    "FournisseurID": "2",
    "CategorieID": "2",
    "QuantitieParUnite": "48 - 6 oz jars",
    "PrixUnitaire": "22.0000",
    "UnityDansStock": "53"
  },
  {
    "Id": "5",
    "Nom": "Chef Anton's Gumbo Mix",
    "FournisseurID": "2",
    "CategorieID": "2",
    "QuantitieParUnite": "36 boxes",
    "PrixUnitaire": "21.3500",
    "UnityDansStock": "0"
  },
  {
    "Id": "6",
    "Nom": "Grandma's Boysenberry Spread",
    "FournisseurID": "3",
    "CategorieID": "2",
    "QuantitieParUnite": "12 - 8 oz jars",
    "PrixUnitaire": "25.0000",
    "UnityDansStock": "120"
  },
  {
    "Id": "7",
    "Nom": "Uncle Bob's Organic Dried Pears",
    "FournisseurID": "3",
    "CategorieID": "7",
    "QuantitieParUnite": "12 - 1 lb pkgs.",
    "PrixUnitaire": "30.0000",
    "UnityDansStock": "15"
  },
  {
    "Id": "8",
    "Nom": "Northwoods Cranberry Sauce",
    "FournisseurID": "3",
    "CategorieID": "2",
    "QuantitieParUnite": "12 - 12 oz jars",
    "PrixUnitaire": "40.0000",
    "UnityDansStock": "6"
  },
  {
    "Id": "9",
    "Nom": "Mishi Kobe Niku",
    "FournisseurID": "4",
    "CategorieID": "6",
    "QuantitieParUnite": "18 - 500 g pkgs.",
    "PrixUnitaire": "97.0000",
    "UnityDansStock": "29"
  },
  {
    "Id": "10",
    "Nom": "Ikura",
    "FournisseurID": "4",
    "CategorieID": "8",
    "QuantitieParUnite": "12 - 200 ml jars",
    "PrixUnitaire": "31.0000",
    "UnityDansStock": "31"
  },
  {
    "Id": "11",
    "Nom": "Queso Cabrales",
    "FournisseurID": "5",
    "CategorieID": "4",
    "QuantitieParUnite": "1 kg pkg.",
    "PrixUnitaire": "21.0000",
    "UnityDansStock": "22"
  },
  {
    "Id": "12",
    "Nom": "Queso Manchego La Pastora",
    "FournisseurID": "5",
    "CategorieID": "4",
    "QuantitieParUnite": "10 - 500 g pkgs.",
    "PrixUnitaire": "38.0000",
    "UnityDansStock": "86"
  },
  {
    "Id": "13",
    "Nom": "Konbu",
    "FournisseurID": "6",
    "CategorieID": "8",
    "QuantitieParUnite": "2 kg box",
    "PrixUnitaire": "6.0000",
    "UnityDansStock": "24"
  },
  {
    "Id": "14",
    "Nom": "Tofu",
    "FournisseurID": "6",
    "CategorieID": "7",
    "QuantitieParUnite": "40 - 100 g pkgs.",
    "PrixUnitaire": "23.2500",
    "UnityDansStock": "35"
  },
  {
    "Id": "15",
    "Nom": "Genen Shouyu",
    "FournisseurID": "6",
    "CategorieID": "2",
    "QuantitieParUnite": "24 - 250 ml bottles",
    "PrixUnitaire": "15.5000",
    "UnityDansStock": "39"
  },
  {
    "Id": "16",
    "Nom": "Pavlova",
    "FournisseurID": "7",
    "CategorieID": "3",
    "QuantitieParUnite": "32 - 500 g boxes",
    "PrixUnitaire": "17.4500",
    "UnityDansStock": "29"
  },
  {
    "Id": "17",
    "Nom": "Alice Mutton",
    "FournisseurID": "7",
    "CategorieID": "6",
    "QuantitieParUnite": "20 - 1 kg tins",
    "PrixUnitaire": "39.0000",
    "UnityDansStock": "0"
  },
  {
    "Id": "18",
    "Nom": "Carnarvon Tigers",
    "FournisseurID": "7",
    "CategorieID": "8",
    "QuantitieParUnite": "16 kg pkg.",
    "PrixUnitaire": "62.5000",
    "UnityDansStock": "42"
  },
  {
    "Id": "19",
    "Nom": "Teatime Chocolate Biscuits",
    "FournisseurID": "8",
    "CategorieID": "3",
    "QuantitieParUnite": "10 boxes x 12 pieces",
    "PrixUnitaire": "9.2000",
    "UnityDansStock": "25"
  },
  {
    "Id": "20",
    "Nom": "Sir Rodney's Marmalade",
    "FournisseurID": "8",
    "CategorieID": "3",
    "QuantitieParUnite": "30 gift boxes",
    "PrixUnitaire": "81.0000",
    "UnityDansStock": "40"
  },
  {
    "Id": "21",
    "Nom": "Sir Rodney's Scones",
    "FournisseurID": "8",
    "CategorieID": "3",
    "QuantitieParUnite": "24 pkgs. x 4 pieces",
    "PrixUnitaire": "10.0000",
    "UnityDansStock": "3"
  },
  {
    "Id": "22",
    "Nom": "Gustaf's Knäckebröd",
    "FournisseurID": "9",
    "CategorieID": "5",
    "QuantitieParUnite": "24 - 500 g pkgs.",
    "PrixUnitaire": "21.0000",
    "UnityDansStock": "104"
  },
  {
    "Id": "23",
    "Nom": "Tunnbröd",
    "FournisseurID": "9",
    "CategorieID": "5",
    "QuantitieParUnite": "12 - 250 g pkgs.",
    "PrixUnitaire": "9.0000",
    "UnityDansStock": "61"
  },
  {
    "Id": "24",
    "Nom": "Guaraná Fantástica",
    "FournisseurID": "10",
    "CategorieID": "1",
    "QuantitieParUnite": "12 - 355 ml cans",
    "PrixUnitaire": "4.5000",
    "UnityDansStock": "20"
  },
  {
    "Id": "25",
    "Nom": "NuNuCa Nuß-Nougat-Creme",
    "FournisseurID": "11",
    "CategorieID": "3",
    "QuantitieParUnite": "20 - 450 g glasses",
    "PrixUnitaire": "14.0000",
    "UnityDansStock": "76"
  },
  {
    "Id": "26",
    "Nom": "Gumbär Gummibärchen",
    "FournisseurID": "11",
    "CategorieID": "3",
    "QuantitieParUnite": "100 - 250 g bags",
    "PrixUnitaire": "31.2300",
    "UnityDansStock": "15"
  },
  {
    "Id": "27",
    "Nom": "Schoggi Schokolade",
    "FournisseurID": "11",
    "CategorieID": "3",
    "QuantitieParUnite": "100 - 100 g pieces",
    "PrixUnitaire": "43.9000",
    "UnityDansStock": "49"
  },
  {
    "Id": "28",
    "Nom": "Rössle Sauerkraut",
    "FournisseurID": "12",
    "CategorieID": "7",
    "QuantitieParUnite": "25 - 825 g cans",
    "PrixUnitaire": "45.6000",
    "UnityDansStock": "26"
  },
  {
    "Id": "29",
    "Nom": "Thüringer Rostbratwurst",
    "FournisseurID": "12",
    "CategorieID": "6",
    "QuantitieParUnite": "50 bags x 30 sausgs.",
    "PrixUnitaire": "123.7900",
    "UnityDansStock": "0"
  },
  {
    "Id": "30",
    "Nom": "Nord-Ost Matjeshering",
    "FournisseurID": "13",
    "CategorieID": "8",
    "QuantitieParUnite": "10 - 200 g glasses",
    "PrixUnitaire": "25.8900",
    "UnityDansStock": "10"
  },
  {
    "Id": "31",
    "Nom": "Gorgonzola Telino",
    "FournisseurID": "14",
    "CategorieID": "4",
    "QuantitieParUnite": "12 - 100 g pkgs",
    "PrixUnitaire": "12.5000",
    "UnityDansStock": "0"
  },
  {
    "Id": "32",
    "Nom": "Mascarpone Fabioli",
    "FournisseurID": "14",
    "CategorieID": "4",
    "QuantitieParUnite": "24 - 200 g pkgs.",
    "PrixUnitaire": "32.0000",
    "UnityDansStock": "9"
  },
  {
    "Id": "33",
    "Nom": "Geitost",
    "FournisseurID": "15",
    "CategorieID": "4",
    "QuantitieParUnite": "500 g",
    "PrixUnitaire": "2.5000",
    "UnityDansStock": "112"
  },
  {
    "Id": "34",
    "Nom": "Sasquatch Ale",
    "FournisseurID": "16",
    "CategorieID": "1",
    "QuantitieParUnite": "24 - 12 oz bottles",
    "PrixUnitaire": "14.0000",
    "UnityDansStock": "111"
  },
  {
    "Id": "35",
    "Nom": "Steeleye Stout",
    "FournisseurID": "16",
    "CategorieID": "1",
    "QuantitieParUnite": "24 - 12 oz bottles",
    "PrixUnitaire": "18.0000",
    "UnityDansStock": "20"
  },
  {
    "Id": "36",
    "Nom": "Inlagd Sill",
    "FournisseurID": "17",
    "CategorieID": "8",
    "QuantitieParUnite": "24 - 250 g  jars",
    "PrixUnitaire": "19.0000",
    "UnityDansStock": "112"
  },
  {
    "Id": "37",
    "Nom": "Gravad lax",
    "FournisseurID": "17",
    "CategorieID": "8",
    "QuantitieParUnite": "12 - 500 g pkgs.",
    "PrixUnitaire": "26.0000",
    "UnityDansStock": "11"
  },
  {
    "Id": "38",
    "Nom": "Côte de Blaye",
    "FournisseurID": "18",
    "CategorieID": "1",
    "QuantitieParUnite": "12 - 75 cl bottles",
    "PrixUnitaire": "263.5000",
    "UnityDansStock": "17"
  },
  {
    "Id": "39",
    "Nom": "Chartreuse verte",
    "FournisseurID": "18",
    "CategorieID": "1",
    "QuantitieParUnite": "750 cc per bottle",
    "PrixUnitaire": "18.0000",
    "UnityDansStock": "69"
  },
  {
    "Id": "40",
    "Nom": "Boston Crab Meat",
    "FournisseurID": "19",
    "CategorieID": "8",
    "QuantitieParUnite": "24 - 4 oz tins",
    "PrixUnitaire": "18.4000",
    "UnityDansStock": "123"
  },
  {
    "Id": "41",
    "Nom": "Jack's New England Clam Chowder",
    "FournisseurID": "19",
    "CategorieID": "8",
    "QuantitieParUnite": "12 - 12 oz cans",
    "PrixUnitaire": "9.6500",
    "UnityDansStock": "85"
  },
  {
    "Id": "42",
    "Nom": "Singaporean Hokkien Fried Mee",
    "FournisseurID": "20",
    "CategorieID": "5",
    "QuantitieParUnite": "32 - 1 kg pkgs.",
    "PrixUnitaire": "14.0000",
    "UnityDansStock": "26"
  },
  {
    "Id": "43",
    "Nom": "Ipoh Coffee",
    "FournisseurID": "20",
    "CategorieID": "1",
    "QuantitieParUnite": "16 - 500 g tins",
    "PrixUnitaire": "46.0000",
    "UnityDansStock": "17"
  },
  {
    "Id": "44",
    "Nom": "Gula Malacca",
    "FournisseurID": "20",
    "CategorieID": "2",
    "QuantitieParUnite": "20 - 2 kg bags",
    "PrixUnitaire": "19.4500",
    "UnityDansStock": "27"
  },
  {
    "Id": "45",
    "Nom": "Rogede sild",
    "FournisseurID": "21",
    "CategorieID": "8",
    "QuantitieParUnite": "1k pkg.",
    "PrixUnitaire": "9.5000",
    "UnityDansStock": "5"
  },
  {
    "Id": "46",
    "Nom": "Spegesild",
    "FournisseurID": "21",
    "CategorieID": "8",
    "QuantitieParUnite": "4 - 450 g glasses",
    "PrixUnitaire": "12.0000",
    "UnityDansStock": "95"
  },
  {
    "Id": "47",
    "Nom": "Zaanse koeken",
    "FournisseurID": "22",
    "CategorieID": "3",
    "QuantitieParUnite": "10 - 4 oz boxes",
    "PrixUnitaire": "9.5000",
    "UnityDansStock": "36"
  },
  {
    "Id": "48",
    "Nom": "Chocolade",
    "FournisseurID": "22",
    "CategorieID": "3",
    "QuantitieParUnite": "10 pkgs.",
    "PrixUnitaire": "12.7500",
    "UnityDansStock": "15"
  },
  {
    "Id": "49",
    "Nom": "Maxilaku",
    "FournisseurID": "23",
    "CategorieID": "3",
    "QuantitieParUnite": "24 - 50 g pkgs.",
    "PrixUnitaire": "20.0000",
    "UnityDansStock": "10"
  },
  {
    "Id": "50",
    "Nom": "Valkoinen suklaa",
    "FournisseurID": "23",
    "CategorieID": "3",
    "QuantitieParUnite": "12 - 100 g bars",
    "PrixUnitaire": "16.2500",
    "UnityDansStock": "65"
  },
  {
    "Id": "51",
    "Nom": "Manjimup Dried Apples",
    "FournisseurID": "24",
    "CategorieID": "7",
    "QuantitieParUnite": "50 - 300 g pkgs.",
    "PrixUnitaire": "53.0000",
    "UnityDansStock": "20"
  },
  {
    "Id": "52",
    "Nom": "Filo Mix",
    "FournisseurID": "24",
    "CategorieID": "5",
    "QuantitieParUnite": "16 - 2 kg boxes",
    "PrixUnitaire": "7.0000",
    "UnityDansStock": "38"
  },
  {
    "Id": "53",
    "Nom": "Perth Pasties",
    "FournisseurID": "24",
    "CategorieID": "6",
    "QuantitieParUnite": "48 pieces",
    "PrixUnitaire": "32.8000",
    "UnityDansStock": "0"
  },
  {
    "Id": "54",
    "Nom": "Tourtière",
    "FournisseurID": "25",
    "CategorieID": "6",
    "QuantitieParUnite": "16 pies",
    "PrixUnitaire": "7.4500",
    "UnityDansStock": "21"
  },
  {
    "Id": "55",
    "Nom": "Pâté chinois",
    "FournisseurID": "25",
    "CategorieID": "6",
    "QuantitieParUnite": "24 boxes x 2 pies",
    "PrixUnitaire": "24.0000",
    "UnityDansStock": "115"
  },
  {
    "Id": "56",
    "Nom": "Gnocchi di nonna Alice",
    "FournisseurID": "26",
    "CategorieID": "5",
    "QuantitieParUnite": "24 - 250 g pkgs.",
    "PrixUnitaire": "38.0000",
    "UnityDansStock": "21"
  },
  {
    "Id": "57",
    "Nom": "Ravioli Angelo",
    "FournisseurID": "26",
    "CategorieID": "5",
    "QuantitieParUnite": "24 - 250 g pkgs.",
    "PrixUnitaire": "19.5000",
    "UnityDansStock": "36"
  },
  {
    "Id": "58",
    "Nom": "Escargots de Bourgogne",
    "FournisseurID": "27",
    "CategorieID": "8",
    "QuantitieParUnite": "24 pieces",
    "PrixUnitaire": "13.2500",
    "UnityDansStock": "62"
  },
  {
    "Id": "59",
    "Nom": "Raclette Courdavault",
    "FournisseurID": "28",
    "CategorieID": "4",
    "QuantitieParUnite": "5 kg pkg.",
    "PrixUnitaire": "55.0000",
    "UnityDansStock": "79"
  },
  {
    "Id": "60",
    "Nom": "Camembert Pierrot",
    "FournisseurID": "28",
    "CategorieID": "4",
    "QuantitieParUnite": "15 - 300 g rounds",
    "PrixUnitaire": "34.0000",
    "UnityDansStock": "19"
  },
  {
    "Id": "61",
    "Nom": "Sirop d'érable",
    "FournisseurID": "29",
    "CategorieID": "2",
    "QuantitieParUnite": "24 - 500 ml bottles",
    "PrixUnitaire": "28.5000",
    "UnityDansStock": "113"
  },
  {
    "Id": "62",
    "Nom": "Tarte au sucre",
    "FournisseurID": "29",
    "CategorieID": "3",
    "QuantitieParUnite": "48 pies",
    "PrixUnitaire": "49.3000",
    "UnityDansStock": "17"
  },
  {
    "Id": "63",
    "Nom": "Vegie-spread",
    "FournisseurID": "7",
    "CategorieID": "2",
    "QuantitieParUnite": "15 - 625 g jars",
    "PrixUnitaire": "43.9000",
    "UnityDansStock": "24"
  },
  {
    "Id": "64",
    "Nom": "Wimmers gute Semmelknödel",
    "FournisseurID": "12",
    "CategorieID": "5",
    "QuantitieParUnite": "20 bags x 4 pieces",
    "PrixUnitaire": "33.2500",
    "UnityDansStock": "22"
  },
  {
    "Id": "65",
    "Nom": "Louisiana Fiery Hot Pepper Sauce",
    "FournisseurID": "2",
    "CategorieID": "2",
    "QuantitieParUnite": "32 - 8 oz bottles",
    "PrixUnitaire": "21.0500",
    "UnityDansStock": "76"
  },
  {
    "Id": "66",
    "Nom": "Louisiana Hot Spiced Okra",
    "FournisseurID": "2",
    "CategorieID": "2",
    "QuantitieParUnite": "24 - 8 oz jars",
    "PrixUnitaire": "17.0000",
    "UnityDansStock": "4"
  },
  {
    "Id": "67",
    "Nom": "Laughing Lumberjack Lager",
    "FournisseurID": "16",
    "CategorieID": "1",
    "QuantitieParUnite": "24 - 12 oz bottles",
    "PrixUnitaire": "14.0000",
    "UnityDansStock": "52"
  },
  {
    "Id": "68",
    "Nom": "Scottish Longbreads",
    "FournisseurID": "8",
    "CategorieID": "3",
    "QuantitieParUnite": "10 boxes x 8 pieces",
    "PrixUnitaire": "12.5000",
    "UnityDansStock": "6"
  },
  {
    "Id": "69",
    "Nom": "Gudbrandsdalsost",
    "FournisseurID": "15",
    "CategorieID": "4",
    "QuantitieParUnite": "10 kg pkg.",
    "PrixUnitaire": "36.0000",
    "UnityDansStock": "26"
  },
  {
    "Id": "70",
    "Nom": "Outback Lager",
    "FournisseurID": "7",
    "CategorieID": "1",
    "QuantitieParUnite": "24 - 355 ml bottles",
    "PrixUnitaire": "15.0000",
    "UnityDansStock": "15"
  },
  {
    "Id": "71",
    "Nom": "Flotemysost",
    "FournisseurID": "15",
    "CategorieID": "4",
    "QuantitieParUnite": "10 - 500 g pkgs.",
    "PrixUnitaire": "21.5000",
    "UnityDansStock": "26"
  },
  {
    "Id": "72",
    "Nom": "Mozzarella di Giovanni",
    "FournisseurID": "14",
    "CategorieID": "4",
    "QuantitieParUnite": "24 - 200 g pkgs.",
    "PrixUnitaire": "34.8000",
    "UnityDansStock": "14"
  },
  {
    "Id": "73",
    "Nom": "Röd Kaviar",
    "FournisseurID": "17",
    "CategorieID": "8",
    "QuantitieParUnite": "24 - 150 g jars",
    "PrixUnitaire": "15.0000",
    "UnityDansStock": "101"
  },
  {
    "Id": "74",
    "Nom": "Longlife Tofu",
    "FournisseurID": "4",
    "CategorieID": "7",
    "QuantitieParUnite": "5 kg pkg.",
    "PrixUnitaire": "10.0000",
    "UnityDansStock": "4"
  },
  {
    "Id": "75",
    "Nom": "Rhönbräu Klosterbier",
    "FournisseurID": "12",
    "CategorieID": "1",
    "QuantitieParUnite": "24 - 0.5 l bottles",
    "PrixUnitaire": "7.7500",
    "UnityDansStock": "125"
  },
  {
    "Id": "76",
    "Nom": "Lakkalikööri",
    "FournisseurID": "23",
    "CategorieID": "1",
    "QuantitieParUnite": "500 ml",
    "PrixUnitaire": "18.0000",
    "UnityDansStock": "57"
  },
  {
    "Id": "77",
    "Nom": "Original Frankfurter grüne Soße",
    "FournisseurID": "12",
    "CategorieID": "2",
    "QuantitieParUnite": "12 boxes",
    "PrixUnitaire": "13.0000",
    "UnityDansStock": "32"
  }
]